CHANGES.txt
LICENSE
MANIFEST.in
README.rst
setup.py
src/celery_longterm_scheduler/__init__.py
src/celery_longterm_scheduler/backend.py
src/celery_longterm_scheduler/conftest.py
src/celery_longterm_scheduler/scheduler.py
src/celery_longterm_scheduler/task.py
src/celery_longterm_scheduler.egg-info/PKG-INFO
src/celery_longterm_scheduler.egg-info/SOURCES.txt
src/celery_longterm_scheduler.egg-info/dependency_links.txt
src/celery_longterm_scheduler.egg-info/entry_points.txt
src/celery_longterm_scheduler.egg-info/not-zip-safe
src/celery_longterm_scheduler.egg-info/requires.txt
src/celery_longterm_scheduler.egg-info/top_level.txt
src/celery_longterm_scheduler/tests/__init__.py
src/celery_longterm_scheduler/tests/test_backend.py
src/celery_longterm_scheduler/tests/test_scheduler.py
src/celery_longterm_scheduler/tests/test_task.py