Metadata-Version: 2.1
Name: celery-longterm-scheduler
Version: 1.3.0
Summary: Schedules celery tasks to run in the potentially far future
Home-page: https://github.com/zeitonline/celery_longterm_scheduler
Author: Zeit Online
Author-email: zon-backend@zeit.de
License: BSD
Classifier: Programming Language :: Python
Classifier: Programming Language :: Python :: 3
Classifier: Programming Language :: Python :: 3.6
License-File: LICENSE
Requires-Dist: celery>=5.0.0.dev0
Requires-Dist: click
Requires-Dist: pendulum
Requires-Dist: redis>=3.0
Requires-Dist: setuptools
Provides-Extra: test
Requires-Dist: pytest; extra == "test"
Requires-Dist: testing.redis; extra == "test"
